orochi/__init__.py
orochi/api.py
orochi/asyncproc.py
orochi/client.py
orochi/colors.py
orochi/errors.py
orochi/meta.py
orochi/player.py
orochi/xdg.py
orochi-0.2.1.dist-info/DESCRIPTION.rst
orochi-0.2.1.dist-info/METADATA
orochi-0.2.1.dist-info/RECORD
orochi-0.2.1.dist-info/WHEEL
orochi-0.2.1.dist-info/entry_points.txt
orochi-0.2.1.dist-info/metadata.json
orochi-0.2.1.dist-info/top_level.txt
tests/__init__.py
tests/test_asyncproc.py
tests/test_client.py
tests/test_colors.py
tests/test_mpd_backend.py
tests/test_testing.py
