Metadata-Version: 2.0
Name: orochi
Version: 0.2.1
Summary: A command line client for 8tracks.com.
Home-page: https://github.com/dbrgn/orochi
Author: Danilo Bargen
Author-email: gezuru@gmail.com
License: GPLv3
Keywords: orochi music playlists 8tracks eighttracks mplayer player
Platform: UNKNOWN
Classifier: Development Status :: 4 - Beta
Classifier: Environment :: Console
Classifier: License :: OSI Approved :: GNU General Public License (GPL)
Classifier: Natural Language :: English
Classifier: Operating System :: MacOS
Classifier: Operating System :: POSIX :: Linux
Classifier: Programming Language :: Python :: 2
Classifier: Programming Language :: Python :: 2.7
Classifier: Programming Language :: Python :: 3
Classifier: Programming Language :: Python :: 3.3
Classifier: Programming Language :: Python :: 3.4
Classifier: Programming Language :: Python :: 3.5
Classifier: Topic :: Internet
Classifier: Topic :: Multimedia :: Sound/Audio :: Players
Classifier: Topic :: Terminals
Requires-Dist: requests (<3,>=1.2.0)
